SimpleNeuro/SimpleNeuro.py
SimpleNeuro/__init__.py
SimpleNeuro-1.0.0.dist-info/METADATA
SimpleNeuro-1.0.0.dist-info/WHEEL
SimpleNeuro-1.0.0.dist-info/top_level.txt
SimpleNeuro-1.0.0.dist-info/RECORD
