Metadata-Version: 2.1
Name: SimpleNeuro
Version: 1.0.0
Home-page: https://github.com/ProDanil3546/Neural-lib.git
Author: Danil
Author-email: radcenkodanil48@gmail.com
License: GNU General Public License v3.0, see LICENSE file
Requires-Dist: numpy (==1.25.2)
